README.txt
setup.py
collective/__init__.py
collective.tinymcetemplates.egg-info/PKG-INFO
collective.tinymcetemplates.egg-info/SOURCES.txt
collective.tinymcetemplates.egg-info/dependency_links.txt
collective.tinymcetemplates.egg-info/entry_points.txt
collective.tinymcetemplates.egg-info/namespace_packages.txt
collective.tinymcetemplates.egg-info/not-zip-safe
collective.tinymcetemplates.egg-info/requires.txt
collective.tinymcetemplates.egg-info/top_level.txt
collective/tinymcetemplates/__init__.py
collective/tinymcetemplates/browser.py
collective/tinymcetemplates/configure.zcml
collective/tinymcetemplates/plugin/blank.htm
collective/tinymcetemplates/plugin/editor_plugin.js
collective/tinymcetemplates/plugin/template.htm
collective/tinymcetemplates/plugin/css/content.css
collective/tinymcetemplates/plugin/css/template.css
collective/tinymcetemplates/plugin/js/template.js
collective/tinymcetemplates/plugin/langs/en_dlg.js
collective/tinymcetemplates/profiles/default/metadata.xml
collective/tinymcetemplates/profiles/default/registry.xml
collective/tinymcetemplates/profiles/default/tinymce.xml
docs/HISTORY.txt