Metadata-Version: 1.0
Name: collective.tinymcetemplates
Version: 1.0b3
Summary: TinyMCE Plugin for templates and snippets
Home-page: http://pypi.python.org/pypi/collective.tinymcetemplates
Author: Rob Gietema
Author-email: rob@fourdigits.nl
License: GPL
Keywords: TinyMCE Plone template snippet
Platform: UNKNOWN
Classifier: Programming Language :: Python
